MANIFEST.in
README.md
setup.cfg
setup.py
ftg.egg-info/PKG-INFO
ftg.egg-info/SOURCES.txt
ftg.egg-info/dependency_links.txt
ftg.egg-info/entry_points.txt
ftg.egg-info/top_level.txt
src/__init__.py
src/__main__.py
src/templates.py
src/files/__init__.py
src/files/app.py
src/files/env.py
src/files/gitignore.py
src/files/readme.py
src/files/start.py
src/files/templates_layout.py
src/files/static/config.py
src/files/static/database.py
src/files/static/migrate.py
src/files/static/requirements.txt
src/files/static/api/__init__.py
src/files/static/api/blueprints/users/views.py
src/files/static/models/__init__.py
src/files/static/models/base_model.py
src/files/static/web/__init__.py
src/files/static/web/blueprints/users/views.py
src/files/static/web/blueprints/users/templates/users/new.html
src/files/static/web/static/css/custom.css
src/files/static/web/static/css/vendor/bootstrap-4.1.3.css
src/files/static/web/static/js/custom.js
src/files/static/web/static/js/vendor/bootstrap-4.1.3.js
src/files/static/web/static/js/vendor/jquery-3.3.1.js
src/files/static/web/static/js/vendor/popper.js
src/files/static/web/templates/500.html
src/files/static/web/templates/home.html
src/files/static/web/util/assets.py
src/utils/__init__.py
src/utils/write_file.py