Metadata-Version: 1.1
Name: ftg
Version: 1.3
Summary: A generator for a flask app template
Home-page: https://github.com/qaqaqaqaowh/ftg
Author: Nicholas Ong Wei Harn
Author-email: nicholasowh@hotmail.com
License: MIT
Download-URL: https://github.com/qaqaqaqaowh/ftg/archive/1.3.tar.gz
Keywords: flask,template,generate
Platform: UNKNOWN
Classifier: Development Status :: 3 - Alpha
Classifier: Intended Audience :: Developers
Classifier: Topic :: Software Development :: Build Tools
Classifier: License :: OSI Approved :: MIT License
Classifier: Programming Language :: Python :: 3
